tcheckerpy/libtchecker.so
tcheckerpy/tools/tck_compare.py
tcheckerpy/tools/tck_liveness.py
tcheckerpy/tools/tck_reach.py
tcheckerpy/tools/tck_simulate.py
tcheckerpy/tools/tck_syntax.py
tcheckerpy/utils/call_tchecker.py
tcheckerpy/utils/tchecker_caller.py
tcheckerpy-2026.1.31.dist-info/licenses/LICENSE
tcheckerpy-2026.1.31.dist-info/METADATA
tcheckerpy-2026.1.31.dist-info/WHEEL
tcheckerpy-2026.1.31.dist-info/top_level.txt
tcheckerpy-2026.1.31.dist-info/RECORD
