Metadata-Version: 2.4
Name: tcheckerpy
Version: 2026.1.31
Summary: A Python Interface for TChecker
Author-email: Alexander Lieb <alexander.lieb@online.de>, Jacob Deuchert <jacob.deuchert@stud.tu-darmstadt.de>, Paula Troszt <paula.troszt@gmx.de>
License-Expression: MIT
Project-URL: Homepage, https://github.com/Echtzeitsysteme/tcheckerpy
Project-URL: Issues, https://github.com/Echtzeitsysteme/tcheckerpy/issues
Classifier: Programming Language :: Python :: 3
Classifier: Operating System :: POSIX :: Linux
Requires-Python: >=3.9
License-File: LICENSE
Dynamic: license-file
